<PAMDataset>
  <PAMRasterBand band="1">
    <Histograms>
      <HistItem>
        <HistMin>28.50520833333333</HistMin>
        <HistMax>124.4947916666667</HistMax>
        <BucketCount>96</BucketCount>
        <IncludeOutOfRange>0</IncludeOutOfRange>
        <Approximate>0</Approximate>
        <HistCounts>2|19|144|751|2530|6241|9418|11606|9698|9350|8923|8887|8879|8878|7364|7590|8725|9098|9254|9684|10725|12414|12948|13461|13554|13349|12208|10036|8140|6413|4824|3657|2518|1797|1275|868|610|444|329|256|157|87|89|56|46|60|43|26|26|21|22|17|9|11|8|7|5|8|7|4|8|2|5|6|5|5|3|3|2|4|3|1|2|2|3|3|3|1|0|1|1|0|0|0|1|0|1|1|0|2|1|1|1|0|0|1</HistCounts>
      </HistItem>
    </Histograms>
    <Metadata>
      <MDI key="STATISTICS_MAXIMUM">124</MDI>
      <MDI key="STATISTICS_MEAN">47.360140931373</MDI>
      <MDI key="STATISTICS_MINIMUM">29</MDI>
      <MDI key="STATISTICS_STDDEV">7.9983340788747</MDI>
      <MDI key="STATISTICS_VALID_PERCENT">100</MDI>
    </Metadata>
  </PAMRasterBand>
  <PAMRasterBand band="2">
    <Histograms>
      <HistItem>
        <HistMin>14.50396825396825</HistMin>
        <HistMax>140.4960317460317</HistMax>
        <BucketCount>126</BucketCount>
        <IncludeOutOfRange>0</IncludeOutOfRange>
        <Approximate>0</Approximate>
        <HistCounts>2|6|15|39|84|155|245|456|1022|1794|3188|5523|6715|7099|7341|7150|6594|6295|5698|5892|5920|5994|5715|4964|4902|4873|5044|5090|5248|5294|5608|5935|6462|6748|7170|7645|7467|7673|7701|7702|7889|7589|7331|7000|6328|5958|5274|4615|4339|3664|3251|2761|2333|1956|1687|1452|1203|979|779|662|504|381|279|210|133|119|76|85|48|45|36|31|35|17|17|10|6|5|5|9|7|5|2|5|2|1|4|2|4|5|0|4|1|5|4|2|1|2|4|0|1|2|4|3|0|3|1|0|0|0|1|1|0|0|1|0|0|0|0|1|0|0|0|0|0|1</HistCounts>
      </HistItem>
    </Histograms>
    <Metadata>
      <MDI key="STATISTICS_MAXIMUM">140</MDI>
      <MDI key="STATISTICS_MEAN">46.151082765423</MDI>
      <MDI key="STATISTICS_MINIMUM">15</MDI>
      <MDI key="STATISTICS_STDDEV">12.893552050905</MDI>
      <MDI key="STATISTICS_VALID_PERCENT">100</MDI>
    </Metadata>
  </PAMRasterBand>
  <PAMRasterBand band="3">
    <Histograms>
      <HistItem>
        <HistMin>3.503267973856209</HistMin>
        <HistMax>156.4967320261438</HistMax>
        <BucketCount>153</BucketCount>
        <IncludeOutOfRange>0</IncludeOutOfRange>
        <Approximate>0</Approximate>
        <HistCounts>2|0|0|3|5|9|23|52|94|225|1204|1102|1239|1730|2551|3271|4092|4602|4679|5055|4034|3984|3713|3450|3264|3278|3118|3042|2926|2905|2848|2891|2815|2730|2771|2788|2673|2668|2637|2626|2693|2685|2721|2792|2878|2853|3059|2947|2973|2939|3130|3196|3307|3329|3591|3856|3965|4133|4252|4166|4341|4753|4590|4624|4878|4724|4751|4746|4680|4482|4537|4573|4206|3932|3956|3685|3504|3375|3120|2907|2789|2592|2400|2080|1986|1731|1639|1424|1321|1114|1029|831|808|675|598|527|465|414|397|331|295|276|180|170|124|96|82|77|46|24|24|28|17|14|18|11|11|5|11|7|8|0|0|3|1|4|3|1|2|2|3|2|4|2|0|1|1|1|1|0|1|2|1|2|2|2|1|1|0|0|0|0|2</HistCounts>
      </HistItem>
    </Histograms>
    <Metadata>
      <MDI key="STATISTICS_MAXIMUM">156</MDI>
      <MDI key="STATISTICS_MEAN">55.053540471066</MDI>
      <MDI key="STATISTICS_MINIMUM">4</MDI>
      <MDI key="STATISTICS_STDDEV">22.652340659444</MDI>
      <MDI key="STATISTICS_VALID_PERCENT">100</MDI>
    </Metadata>
  </PAMRasterBand>
  <PAMRasterBand band="4">
    <Histograms>
      <HistItem>
        <HistMin>-0.4978448275862069</HistMin>
        <HistMax>231.4978448275862</HistMax>
        <BucketCount>232</BucketCount>
        <IncludeOutOfRange>0</IncludeOutOfRange>
        <Approximate>0</Approximate>
        <HistCounts>36|38|54|82|131|228|1680|2069|648|90|97|72|71|74|55|54|65|51|68|54|59|53|57|50|64|63|70|50|50|75|73|77|74|70|79|110|81|110|90|111|126|108|129|138|149|150|156|174|177|156|189|203|212|248|248|313|309|354|365|409|430|546|580|669|750|873|964|1042|1158|1249|1445|1511|1646|1872|1869|2162|2322|2406|2579|2713|2849|2886|3032|3267|3370|3611|3796|3959|4016|4152|4362|4236|4385|4665|4725|4808|4862|4954|4912|4849|4906|4845|4800|4884|4785|4927|4811|4613|4688|4540|4621|4488|4460|4255|4317|4117|3977|4017|3714|3603|3409|3282|3179|3070|2973|2693|2593|2569|2290|2218|2071|1940|1805|1667|1582|1434|1282|1197|1164|1034|1028|882|784|739|693|600|566|497|438|467|395|364|340|321|320|290|316|260|260|244|239|183|160|150|148|117|102|82|81|54|42|48|39|39|27|32|27|26|27|30|22|20|25|25|29|29|23|23|19|32|24|34|31|34|29|32|39|35|36|33|39|52|69|39|29|33|45|40|30|35|44|34|35|26|33|17|28|26|25|22|31|20|27|12|11|3|6|3|0|2|1|2</HistCounts>
      </HistItem>
    </Histograms>
    <Metadata>
      <MDI key="STATISTICS_MAXIMUM">231</MDI>
      <MDI key="STATISTICS_MEAN">101.110940489</MDI>
      <MDI key="STATISTICS_MINIMUM">0</MDI>
      <MDI key="STATISTICS_STDDEV">26.440302823303</MDI>
      <MDI key="STATISTICS_VALID_PERCENT">100</MDI>
    </Metadata>
  </PAMRasterBand>
</PAMDataset>
